CHANGES.txt
LICENSE.txt
MANIFEST.in
README.txt
bootstrap.py
buildout.cfg
setup.py
src/p01/__init__.py
src/p01.pagelet.egg-info/PKG-INFO
src/p01.pagelet.egg-info/SOURCES.txt
src/p01.pagelet.egg-info/dependency_links.txt
src/p01.pagelet.egg-info/namespace_packages.txt
src/p01.pagelet.egg-info/not-zip-safe
src/p01.pagelet.egg-info/requires.txt
src/p01.pagelet.egg-info/top_level.txt
src/p01/pagelet/README.txt
src/p01/pagelet/__init__.py
src/p01/pagelet/configure.zcml
src/p01/pagelet/interfaces.py
src/p01/pagelet/layer.py
src/p01/pagelet/traverser.py
src/p01/pagelet/traverser.zcml
src/p01/pagelet/browser/__init__.py
src/p01/pagelet/browser/configure.zcml
src/p01/pagelet/browser/notfound.pt
src/p01/pagelet/browser/systemerror.pt
src/p01/pagelet/browser/unauthorized.pt
src/p01/pagelet/browser/user.pt
src/p01/pagelet/tests/__init__.py
src/p01/pagelet/tests/checker.txt
src/p01/pagelet/tests/tests.py